MANIFEST.in
setup.cfg
setup.py
requirements/base.txt
requirements/dev.txt
trading.etl.fetcher.egg-info/PKG-INFO
trading.etl.fetcher.egg-info/SOURCES.txt
trading.etl.fetcher.egg-info/dependency_links.txt
trading.etl.fetcher.egg-info/requires.txt
trading.etl.fetcher.egg-info/top_level.txt
trading/etl/fetcher/__init__.py