Metadata-Version: 2.1
Name: trading.etl.fetcher
Version: 0.0.2
Summary: Exchange OHLCV Fetcher Package used in Trading
Home-page: UNKNOWN
Author: Trading
License: UNKNOWN
Platform: UNKNOWN
Requires-Python: >=3.7
